{
  "$schema": "https://docs.page/schema.json",
  "name": "animated_streaming_markdown",
  "description": "Flutter markdown streaming package for parser workers, block rendering, token animation, and Markdown-aware copy.",
  "logo": {
    "light": "/assets/branding/logo.svg",
    "dark": "/assets/branding/logo.svg"
  },
  "theme": {
    "primary": "#2563EB"
  },
  "header": {
    "links": [
      {
        "title": "pub.dev",
        "href": "https://pub.dev/packages/animated_streaming_markdown"
      },
      {
        "title": "GitHub",
        "href": "https://github.com/samnn152/streaming-markdown"
      }
    ]
  },
  "anchors": [
    {
      "title": "API reference",
      "href": "https://pub.dev/documentation/animated_streaming_markdown/latest/"
    },
    {
      "title": "Issues",
      "href": "https://github.com/samnn152/streaming-markdown/issues"
    }
  ],
  "sidebar": [
    {
      "group": "Getting Started",
      "pages": [
        {
          "title": "Overview",
          "href": "/"
        },
        {
          "title": "Installation",
          "href": "/installation"
        },
        {
          "title": "Quick Start",
          "href": "/quick-start"
        }
      ]
    },
    {
      "group": "Guides",
      "pages": [
        {
          "title": "API Overview",
          "href": "/api-overview"
        },
        {
          "title": "Selection Copy",
          "href": "/selection-copy"
        },
        {
          "title": "Migration 0.2.x to 0.3.x",
          "href": "/migration-0-3"
        }
      ]
    },
    {
      "group": "Project",
      "pages": [
        {
          "title": "Roadmap",
          "href": "/roadmap"
        },
        {
          "title": "Contributing",
          "href": "/contributing"
        }
      ]
    }
  ]
}
